src/__init__.py
src/dimension_calc.py
src/main.py
src/sound_image.py
src/tone_array.py
image2sound-0.5.dist-info/METADATA
image2sound-0.5.dist-info/WHEEL
image2sound-0.5.dist-info/licenses/LICENSE
image2sound-0.5.dist-info/RECORD
