Metadata-Version: 2.1
Name: image2sound
Version: 0.5
Summary: A Python utility that converts images to audio. 
Project-URL: Homepage, https://codeberg.org/jaerrib/image2sound
Project-URL: Bug Tracker, https://codeberg.org/jaerrib/image2sound/issues
Author-email: John Beers <jaerrib@tutanota.com>
License-File: LICENSE
Classifier: License :: OSI Approved :: GNU Affero General Public License v3
Classifier: Operating System :: OS Independent
Classifier: Programming Language :: Python :: 3
Classifier: Topic :: Multimedia :: Sound/Audio :: Conversion
Requires-Python: >=3.7
